MANIFEST.in
README.txt
setup.cfg
setup.py
src/tgext/__init__.py
src/tgext.subform.egg-info/PKG-INFO
src/tgext.subform.egg-info/SOURCES.txt
src/tgext.subform.egg-info/dependency_links.txt
src/tgext.subform.egg-info/entry_points.txt
src/tgext.subform.egg-info/namespace_packages.txt
src/tgext.subform.egg-info/not-zip-safe
src/tgext.subform.egg-info/requires.txt
src/tgext.subform.egg-info/top_level.txt
src/tgext/subform/__init__.py
src/tgext/subform/config.py
src/tgext/subform/controller.py
src/tgext/subform/widgets.py
src/tgext/subform/templates/select_field_with_add.mak
src/tgext/subform/templates/table_subform.mak