Metadata-Version: 1.0
Name: tgext.subform
Version: 1.4
Summary: Allows users to create TG applications with CRUD-cabable ajax subforms.
Home-page: http://svn.plone.org/svn/collective/
Author: Christopher Perkins
Author-email: chris@percious.com
License: mit
Keywords: turbogears tg tgext crud admin
Platform: UNKNOWN
Classifier: Programming Language :: Python
